uibbq.py
uibbq-1.0.dist-info/LICENSE
uibbq-1.0.dist-info/WHEEL
uibbq-1.0.dist-info/METADATA
uibbq-1.0.dist-info/RECORD
