Metadata-Version: 2.1
Name: uibbq
Version: 1.0
Summary: Micropython iBBQ Interface
Home-page: https://github.com/cookejames/uibbq
Author: James Cooke
Author-email: uibbq@jaynne.co.uk
Classifier: License :: OSI Approved :: Apache Software License
